edc_transfer/__init__.py
edc_transfer/action_items.py
edc_transfer/apps.py
edc_transfer/choices.py
edc_transfer/constants.py
edc_transfer/form_validators.py
edc_transfer/model_mixins.py
edc_transfer/modeladmin_mixins.py
edc_transfer/modelform_mixins.py
edc_transfer/models.py
edc_transfer/tests/__init__.py
edc_transfer/tests/admin.py
edc_transfer/tests/forms.py
edc_transfer/tests/holidays.csv
edc_transfer/tests/models.py
edc_transfer/tests/test_settings.py
edc_transfer/tests/urls.py
edc_transfer/tests/etc/user-aes-local.key
edc_transfer/tests/etc/user-aes-restricted.key
edc_transfer/tests/etc/user-rsa-local-private.pem
edc_transfer/tests/etc/user-rsa-local-public.pem
edc_transfer/tests/etc/user-rsa-restricted-private.pem
edc_transfer/tests/etc/user-rsa-restricted-public.pem
edc_transfer/tests/etc/user-salt-local.key
edc_transfer/tests/etc/user-salt-restricted.key
edc_transfer/tests/tests/__init__.py
edc_transfer/tests/tests/tests.py
edc_transfer-1.0.1.dist-info/licenses/AUTHORS
edc_transfer-1.0.1.dist-info/licenses/LICENSE
edc_transfer-1.0.1.dist-info/METADATA
edc_transfer-1.0.1.dist-info/WHEEL
edc_transfer-1.0.1.dist-info/top_level.txt
edc_transfer-1.0.1.dist-info/RECORD
